.hgignore
.version
MANIFEST.in
README.txt
setup.py
.snippets/.snips.rc
doc/Makefile
doc/abbrevs.inc
doc/chapter-footer.snip
doc/chapter-header.snip
doc/conf.py
doc/conf.pyc
doc/doc_defs.inc
doc/doc_defs.snip
doc/doc_defs_combined.inc
doc/doc_defs_standalone.inc
doc/docutils.conf
doc/index-footer.snip
doc/index-header.snip
doc/index.rst.auto
doc/index.rst.generated
doc/make.bat
doc/module.rst_template
doc/overview-footer.snip
doc/overview-header.snip
doc/overview.rst.auto
doc/standalone-footer.snip
doc/standalone-header.snip
doc/_static/bootstrap3-sub-menu.css
doc/_templates/globaltoc.html
snappets/__init__.py
snappets.egg-info/PKG-INFO
snappets.egg-info/SOURCES.txt
snappets.egg-info/dependency_links.txt
snappets.egg-info/top_level.txt