Metadata-Version: 2.1
Name: snappets
Version: 0.0.2
Summary: Snippets in Python
Home-page: https://bitbucket.org/wolfmanx/snappets
Author: Wolfgang Scherer
Author-email: wolfgang.scherer@gmx.de
License: UNKNOWN
Platform: UNKNOWN
Classifier: Programming Language :: Python
Classifier: Programming Language :: Python :: 2
Classifier: Programming Language :: Python :: 3
Classifier: License :: OSI Approved :: GNU General Public License (GPL)
Classifier: Operating System :: OS Independent
